simple_utils/__init__.py
simple_utils/_version.py
simple_utils/platform/__init__.py
simple_utils/platform/duckdb.py
simple_utils/platform/iceberg.py
simple_utils/storage/__init__.py
simple_utils/storage/object_storage.py
simple_utils/utils/__init__.py
simple_utils/utils/argument.py
simple_utils/utils/functions.py
simple_utils/utils/log.ipynb
simple_utils/utils/log.py
simple_utils/utils/notebook.py
simple_utils/utils/schema.py
simple_utils/utils/structure.py
simple_utils/utils/text.py
simple_utils/utils/thread.py
simple_utils/utils/time.ipynb
simple_utils/utils/time.py
simple_utils-16.dist-info/METADATA
simple_utils-16.dist-info/WHEEL
simple_utils-16.dist-info/licenses/LICENSE
simple_utils-16.dist-info/RECORD
