Metadata-Version: 2.4
Name: simple-utils
Version: 16
Summary: A collection of simple Python utilities for datetime, string, file, and decorator operations
Project-URL: Homepage, https://github.com/i-tems/simple-utils
Project-URL: Repository, https://github.com/i-tems/simple-utils
Project-URL: Issues, https://github.com/i-tems/simple-utils/issues
Author-email: da-huin <dahuin000@gmail.com>
License-Expression: MIT
License-File: LICENSE
Keywords: datetime,decorator,file,string,utilities,utils
Classifier: Development Status :: 3 - Alpha
Classifier: Intended Audience :: Developers
Classifier: License :: OSI Approved :: MIT License
Classifier: Operating System :: OS Independent
Classifier: Programming Language :: Python :: 3
Classifier: Programming Language :: Python :: 3.8
Classifier: Programming Language :: Python :: 3.9
Classifier: Programming Language :: Python :: 3.10
Classifier: Programming Language :: Python :: 3.11
Classifier: Programming Language :: Python :: 3.12
Classifier: Topic :: Software Development :: Libraries :: Python Modules
Requires-Python: >=3.8
Requires-Dist: duckdb>=1.0.0
Requires-Dist: jsonschema>=4.0.0
Requires-Dist: pandas>=1.5.0
Requires-Dist: pendulum>=3.0.0
Requires-Dist: pyarrow>=12.0.0
Requires-Dist: pyiceberg[pandas,pyarrow]>=0.10.0
Requires-Dist: python-dateutil>=2.8.0
Requires-Dist: pytz>=2023.0
Requires-Dist: structlog>=23.0.0
Provides-Extra: test
Requires-Dist: pytest>=7.0; extra == 'test'
